setup.py
sphero_sprk/__init__.py
sphero_sprk/sphero.py
sphero_sprk/util.py
sphero_sprk.egg-info/PKG-INFO
sphero_sprk.egg-info/SOURCES.txt
sphero_sprk.egg-info/dependency_links.txt
sphero_sprk.egg-info/requires.txt
sphero_sprk.egg-info/top_level.txt
sphero_sprk/data/mask_list.yaml