Metadata-Version: 1.1
Name: sphero-sprk
Version: 0.1.4
Summary: Python Module that commands Sphero SPRK+
Home-page: https://github.com/CMU-ARM/sphero_sprk
Author: Xiang Zhi Tan
Author-email: zhi.tan@ri.cmu.edu
License: UNKNOWN
Keywords: Sphero,SPRK
Platform: UNKNOWN
Classifier: Development Status :: 3 - Alpha
Classifier: Programming Language :: Python :: 3.3
